taskfeasibilityanalyzer/__init__.py
taskfeasibilityanalyzer/analyzer.py
taskfeasibilityanalyzer-2025.5.180905.dist-info/licenses/LICENSE
tests/__init__.py
tests/test_analyzer.py
taskfeasibilityanalyzer-2025.5.180905.dist-info/METADATA
taskfeasibilityanalyzer-2025.5.180905.dist-info/WHEEL
taskfeasibilityanalyzer-2025.5.180905.dist-info/top_level.txt
taskfeasibilityanalyzer-2025.5.180905.dist-info/RECORD
