Metadata-Version: 2.4
Name: TaskFeasibilityAnalyzer
Version: 2025.5.180905
Summary: A Python package to determine the feasibility of coding tasks using GPT-3.
Home-page: https://github.com/chigwell/TaskFeasibilityAnalyzer
Author: Eugene Evstafev
Author-email: chigwel@gmail.com
Classifier: Programming Language :: Python :: 3
Classifier: License :: OSI Approved :: MIT License
Classifier: Operating System :: OS Independent
Requires-Python: >=3.6
License-File: LICENSE
Requires-Dist: openai
Requires-Dist: projectstructor
Requires-Dist: gptintegration
Dynamic: author
Dynamic: author-email
Dynamic: classifier
Dynamic: description
Dynamic: description-content-type
Dynamic: home-page
Dynamic: license-file
Dynamic: requires-dist
Dynamic: requires-python
Dynamic: summary
